iterfun/__init__.py
iterfun/iterfun.py
iterfun-0.0.5.dist-info/LICENSE
iterfun-0.0.5.dist-info/METADATA
iterfun-0.0.5.dist-info/WHEEL
iterfun-0.0.5.dist-info/top_level.txt
iterfun-0.0.5.dist-info/RECORD
