Metadata-Version: 2.1
Name: iterfun
Version: 0.0.5
Summary: Implements an eager iterator class reminiscent of Elixir's Enum structure.
Home-page: https://github.com/StefanGreve/iterfun
Author: StefanGreve
Author-email: greve.stefan@outlook.jp
License: MIT
Project-URL: Documentation, https://github.com/StefanGreve/iterfun/blob/master/README.md
Project-URL: Source Code, https://github.com/StefanGreve/iterfun
Project-URL: Bug Reports, https://github.com/StefanGreve/iterfun/issues
Project-URL: Changelog, https://github.com/StefanGreve/iterfun/blob/master/CHANGELOG.md
Keywords: utils,functional programming,functools,itertools,extension
Classifier: Development Status :: 4 - Beta
Classifier: License :: OSI Approved :: MIT License
Classifier: Intended Audience :: Developers
Classifier: Natural Language :: English
Classifier: Programming Language :: Python :: 3.8
Classifier: Programming Language :: Python :: 3.9
Classifier: Programming Language :: Python :: 3.10
Classifier: Programming Language :: Python :: 3.11
Classifier: Programming Language :: Python :: 3.12
Classifier: Programming Language :: Python :: Implementation :: CPython
Classifier: Operating System :: OS Independent
Classifier: Topic :: Utilities
Requires-Python: >=3.8
License-File: LICENSE
Requires-Dist: typing-extensions (==4.4.0)
